{
    "instance_name": "TSP-grid-n70-g10000-5",
    "n_customers": 70,
    "dimension": 2,
    "grid_size": 10000,
    "distribution_type": "grid",
    "generation_seed": 1692427,
    "coordinates": [
        [
            567,
            538
        ],
        [
            581,
            1644
        ],
        [
            557,
            2761
        ],
        [
            503,
            3921
        ],
        [
            507,
            5052
        ],
        [
            518,
            6128
        ],
        [
            602,
            7261
        ],
        [
            556,
            8300
        ],
        [
            592,
            9473
        ],
        [
            1711,
            556
        ],
        [
            1716,
            1690
        ],
        [
            1700,
            2810
        ],
        [
            1677,
            3866
        ],
        [
            1693,
            5036
        ],
        [
            1703,
            6099
        ],
        [
            1615,
            7241
        ],
        [
            1717,
            8281
        ],
        [
            1659,
            9392
        ],
        [
            2823,
            579
        ],
        [
            2766,
            1706
        ],
        [
            2792,
            2777
        ],
        [
            2793,
            3871
        ],
        [
            2792,
            4979
        ],
        [
            2733,
            6142
        ],
        [
            2822,
            7214
        ],
        [
            2807,
            8387
        ],
        [
            2827,
            9489
        ],
        [
            3909,
            582
        ],
        [
            3909,
            1662
        ],
        [
            3849,
            2782
        ],
        [
            3910,
            3867
        ],
        [
            3875,
            4971
        ],
        [
            3863,
            6127
        ],
        [
            3851,
            7246
        ],
        [
            3929,
            8291
        ],
        [
            3903,
            9496
        ],
        [
            5013,
            542
        ],
        [
            4998,
            1654
        ],
        [
            5031,
            2729
        ],
        [
            4947,
            3866
        ],
        [
            5000,
            4975
        ],
        [
            5018,
            6125
        ],
        [
            5003,
            7184
        ],
        [
            5041,
            8308
        ],
        [
            5027,
            9459
        ],
        [
            6151,
            601
        ],
        [
            6115,
            1656
        ],
        [
            6063,
            2760
        ],
        [
            6137,
            3857
        ],
        [
            6098,
            4972
        ],
        [
            6119,
            6057
        ],
        [
            6148,
            7221
        ],
        [
            6121,
            8345
        ],
        [
            6156,
            9481
        ],
        [
            7215,
            574
        ],
        [
            7268,
            1622
        ],
        [
            7255,
            2779
        ],
        [
            7184,
            3910
        ],
        [
            7208,
            4947
        ],
        [
            7246,
            6091
        ],
        [
            7187,
            7237
        ],
        [
            7204,
            8286
        ],
        [
            7166,
            9399
        ],
        [
            8351,
            513
        ],
        [
            8301,
            1622
        ],
        [
            8315,
            2795
        ],
        [
            8291,
            3928
        ],
        [
            8388,
            4959
        ],
        [
            8298,
            6127
        ],
        [
            8377,
            7189
        ]
    ]
}