{
    "instance_name": "TSP-uniform_triangular-n400-g10000-2",
    "n_customers": 400,
    "dimension": 2,
    "grid_size": 10000,
    "distribution_type": "uniform_triangular",
    "generation_seed": 2028946,
    "coordinates": [
        [
            914,
            2784
        ],
        [
            2403,
            7106
        ],
        [
            710,
            3614
        ],
        [
            5195,
            1558
        ],
        [
            9641,
            5491
        ],
        [
            1973,
            9173
        ],
        [
            7493,
            5053
        ],
        [
            7967,
            7274
        ],
        [
            556,
            3799
        ],
        [
            3119,
            5472
        ],
        [
            3996,
            3561
        ],
        [
            7189,
            6731
        ],
        [
            6432,
            6874
        ],
        [
            5296,
            6855
        ],
        [
            3848,
            3354
        ],
        [
            4015,
            4822
        ],
        [
            555,
            5320
        ],
        [
            7755,
            6319
        ],
        [
            6798,
            2451
        ],
        [
            7799,
            7838
        ],
        [
            491,
            4201
        ],
        [
            9491,
            2109
        ],
        [
            5773,
            2353
        ],
        [
            76,
            4697
        ],
        [
            7458,
            4379
        ],
        [
            4710,
            6722
        ],
        [
            6497,
            4554
        ],
        [
            8818,
            1780
        ],
        [
            233,
            2570
        ],
        [
            878,
            5032
        ],
        [
            1835,
            6448
        ],
        [
            2268,
            4833
        ],
        [
            6826,
            3858
        ],
        [
            6875,
            4578
        ],
        [
            8362,
            2888
        ],
        [
            8961,
            3107
        ],
        [
            243,
            2515
        ],
        [
            1799,
            6431
        ],
        [
            8541,
            4616
        ],
        [
            1596,
            4187
        ],
        [
            9097,
            5569
        ],
        [
            3029,
            4664
        ],
        [
            3948,
            8911
        ],
        [
            6777,
            8899
        ],
        [
            9850,
            4132
        ],
        [
            5966,
            3669
        ],
        [
            3766,
            6089
        ],
        [
            5523,
            6660
        ],
        [
            1806,
            4355
        ],
        [
            8274,
            6881
        ],
        [
            3426,
            4587
        ],
        [
            5062,
            7877
        ],
        [
            13,
            5686
        ],
        [
            4653,
            3540
        ],
        [
            6075,
            6288
        ],
        [
            6716,
            3344
        ],
        [
            5747,
            3936
        ],
        [
            4172,
            6380
        ],
        [
            1004,
            2852
        ],
        [
            569,
            6552
        ],
        [
            418,
            4222
        ],
        [
            9336,
            6540
        ],
        [
            5049,
            3991
        ],
        [
            4376,
            6419
        ],
        [
            8615,
            6677
        ],
        [
            2097,
            5381
        ],
        [
            670,
            5057
        ],
        [
            6611,
            4997
        ],
        [
            6152,
            1088
        ],
        [
            4302,
            7548
        ],
        [
            4487,
            2707
        ],
        [
            3494,
            1086
        ],
        [
            6814,
            6730
        ],
        [
            8032,
            3363
        ],
        [
            5742,
            5312
        ],
        [
            2053,
            1872
        ],
        [
            3044,
            6277
        ],
        [
            141,
            6963
        ],
        [
            5253,
            4712
        ],
        [
            4578,
            4867
        ],
        [
            1894,
            4314
        ],
        [
            3261,
            5668
        ],
        [
            2710,
            4201
        ],
        [
            5650,
            6332
        ],
        [
            3250,
            8533
        ],
        [
            9692,
            3213
        ],
        [
            2528,
            2826
        ],
        [
            4362,
            5744
        ],
        [
            1305,
            7594
        ],
        [
            9984,
            2725
        ],
        [
            8782,
            6874
        ],
        [
            1274,
            3157
        ],
        [
            9051,
            3380
        ],
        [
            3050,
            4063
        ],
        [
            3712,
            4041
        ],
        [
            4537,
            2980
        ],
        [
            5199,
            7902
        ],
        [
            9674,
            6008
        ],
        [
            5260,
            1113
        ],
        [
            736,
            2052
        ],
        [
            1743,
            3338
        ],
        [
            4771,
            5763
        ],
        [
            3889,
            4916
        ],
        [
            6477,
            3073
        ],
        [
            6229,
            8820
        ],
        [
            8424,
            5274
        ],
        [
            373,
            3102
        ],
        [
            3419,
            714
        ],
        [
            8571,
            6595
        ],
        [
            997,
            4195
        ],
        [
            9012,
            5123
        ],
        [
            7407,
            4967
        ],
        [
            8307,
            7490
        ],
        [
            4353,
            8736
        ],
        [
            263,
            5135
        ],
        [
            8003,
            661
        ],
        [
            4515,
            5172
        ],
        [
            7644,
            6736
        ],
        [
            7123,
            2306
        ],
        [
            2831,
            3229
        ],
        [
            8299,
            5144
        ],
        [
            7359,
            5363
        ],
        [
            9954,
            2783
        ],
        [
            9270,
            8253
        ],
        [
            1645,
            5969
        ],
        [
            9647,
            589
        ],
        [
            3857,
            9083
        ],
        [
            8016,
            5477
        ],
        [
            9228,
            6295
        ],
        [
            1634,
            2738
        ],
        [
            2093,
            6341
        ],
        [
            6350,
            3797
        ],
        [
            5244,
            3456
        ],
        [
            8903,
            4042
        ],
        [
            9804,
            8034
        ],
        [
            7952,
            6612
        ],
        [
            995,
            6734
        ],
        [
            7413,
            5549
        ],
        [
            889,
            8418
        ],
        [
            4401,
            3112
        ],
        [
            7447,
            4548
        ],
        [
            1982,
            5969
        ],
        [
            6869,
            3796
        ],
        [
            7907,
            3320
        ],
        [
            3509,
            1765
        ],
        [
            6902,
            8328
        ],
        [
            9613,
            6622
        ],
        [
            296,
            1087
        ],
        [
            7322,
            6734
        ],
        [
            1594,
            5837
        ],
        [
            5930,
            4776
        ],
        [
            5567,
            3670
        ],
        [
            3376,
            6902
        ],
        [
            9972,
            3611
        ],
        [
            7807,
            2364
        ],
        [
            5371,
            6090
        ],
        [
            8857,
            5424
        ],
        [
            2219,
            4040
        ],
        [
            5478,
            8004
        ],
        [
            179,
            5974
        ],
        [
            9664,
            6572
        ],
        [
            8464,
            6498
        ],
        [
            8329,
            9289
        ],
        [
            5586,
            6276
        ],
        [
            8064,
            2946
        ],
        [
            8802,
            5175
        ],
        [
            9642,
            2347
        ],
        [
            5626,
            8203
        ],
        [
            7436,
            6982
        ],
        [
            8997,
            5074
        ],
        [
            345,
            8106
        ],
        [
            4361,
            4290
        ],
        [
            1408,
            3574
        ],
        [
            5164,
            4712
        ],
        [
            4533,
            4903
        ],
        [
            3365,
            1515
        ],
        [
            5843,
            7732
        ],
        [
            4198,
            5767
        ],
        [
            4019,
            2014
        ],
        [
            2046,
            7557
        ],
        [
            505,
            4003
        ],
        [
            4736,
            3021
        ],
        [
            4768,
            6020
        ],
        [
            1526,
            2987
        ],
        [
            6749,
            5647
        ],
        [
            9474,
            9430
        ],
        [
            5797,
            5491
        ],
        [
            4746,
            4360
        ],
        [
            7921,
            2291
        ],
        [
            5057,
            5518
        ],
        [
            5208,
            2281
        ],
        [
            8482,
            3840
        ],
        [
            5734,
            2437
        ],
        [
            9053,
            1034
        ],
        [
            8175,
            5061
        ],
        [
            4162,
            6654
        ],
        [
            7236,
            1670
        ],
        [
            2302,
            732
        ],
        [
            8039,
            2258
        ],
        [
            9744,
            5734
        ],
        [
            1539,
            4716
        ],
        [
            1928,
            5936
        ],
        [
            8832,
            2209
        ],
        [
            3893,
            3437
        ],
        [
            6004,
            5470
        ],
        [
            3257,
            7736
        ],
        [
            7351,
            5475
        ],
        [
            610,
            4393
        ],
        [
            4385,
            8689
        ],
        [
            4271,
            2992
        ],
        [
            2942,
            3123
        ],
        [
            4401,
            2561
        ],
        [
            9027,
            2641
        ],
        [
            4604,
            3960
        ],
        [
            3128,
            5873
        ],
        [
            2634,
            3602
        ],
        [
            4604,
            5633
        ],
        [
            9470,
            7671
        ],
        [
            8227,
            6423
        ],
        [
            7252,
            5903
        ],
        [
            2426,
            821
        ],
        [
            2003,
            3849
        ],
        [
            8981,
            3894
        ],
        [
            5748,
            7198
        ],
        [
            1903,
            3403
        ],
        [
            5686,
            4507
        ],
        [
            3637,
            4798
        ],
        [
            2053,
            8579
        ],
        [
            7837,
            7492
        ],
        [
            8855,
            2518
        ],
        [
            758,
            7470
        ],
        [
            8189,
            8588
        ],
        [
            6719,
            6473
        ],
        [
            2487,
            4486
        ],
        [
            4587,
            4244
        ],
        [
            1652,
            2389
        ],
        [
            1214,
            8077
        ],
        [
            7705,
            3545
        ],
        [
            9283,
            7049
        ],
        [
            9257,
            6095
        ],
        [
            9961,
            812
        ],
        [
            480,
            5171
        ],
        [
            1147,
            6886
        ],
        [
            6196,
            6247
        ],
        [
            6982,
            5103
        ],
        [
            8507,
            3923
        ],
        [
            1136,
            3492
        ],
        [
            6788,
            4063
        ],
        [
            6805,
            5448
        ],
        [
            2538,
            3849
        ],
        [
            1995,
            6744
        ],
        [
            3078,
            5015
        ],
        [
            8635,
            1659
        ],
        [
            9592,
            8421
        ],
        [
            4381,
            4197
        ],
        [
            5444,
            4984
        ],
        [
            6621,
            2647
        ],
        [
            4220,
            5660
        ],
        [
            1107,
            6677
        ],
        [
            4851,
            6110
        ],
        [
            5270,
            7877
        ],
        [
            7970,
            6425
        ],
        [
            1353,
            3917
        ],
        [
            3347,
            7820
        ],
        [
            1387,
            4405
        ],
        [
            4408,
            6560
        ],
        [
            7823,
            4461
        ],
        [
            2096,
            4259
        ],
        [
            9447,
            6301
        ],
        [
            5047,
            2217
        ],
        [
            1832,
            2050
        ],
        [
            1919,
            7485
        ],
        [
            9072,
            2312
        ],
        [
            3383,
            8534
        ],
        [
            547,
            3908
        ],
        [
            2785,
            1670
        ],
        [
            1246,
            5530
        ],
        [
            7477,
            3460
        ],
        [
            9855,
            4027
        ],
        [
            1069,
            3739
        ],
        [
            8561,
            6639
        ],
        [
            9965,
            1506
        ],
        [
            4791,
            4177
        ],
        [
            8162,
            6470
        ],
        [
            1942,
            4187
        ],
        [
            7053,
            2045
        ],
        [
            3155,
            2810
        ],
        [
            9960,
            3257
        ],
        [
            7695,
            450
        ],
        [
            3298,
            3675
        ],
        [
            6918,
            3899
        ],
        [
            6607,
            1636
        ],
        [
            8794,
            3211
        ],
        [
            7714,
            2741
        ],
        [
            4094,
            6503
        ],
        [
            2019,
            4848
        ],
        [
            4540,
            1418
        ],
        [
            9860,
            3480
        ],
        [
            5750,
            3765
        ],
        [
            849,
            4142
        ],
        [
            4779,
            5027
        ],
        [
            3448,
            4612
        ],
        [
            2634,
            3843
        ],
        [
            6710,
            7410
        ],
        [
            1942,
            6461
        ],
        [
            3158,
            2030
        ],
        [
            3932,
            3136
        ],
        [
            5511,
            6878
        ],
        [
            2079,
            3277
        ],
        [
            8024,
            5340
        ],
        [
            9886,
            420
        ],
        [
            6092,
            8198
        ],
        [
            8749,
            3194
        ],
        [
            3913,
            4519
        ],
        [
            4229,
            6369
        ],
        [
            8568,
            3311
        ],
        [
            8341,
            6255
        ],
        [
            4333,
            608
        ],
        [
            9360,
            4603
        ],
        [
            4225,
            587
        ],
        [
            913,
            4953
        ],
        [
            7040,
            2152
        ],
        [
            2773,
            4610
        ],
        [
            4623,
            2819
        ],
        [
            541,
            6896
        ],
        [
            1121,
            2571
        ],
        [
            7725,
            7715
        ],
        [
            9616,
            1876
        ],
        [
            494,
            1402
        ],
        [
            2965,
            4608
        ],
        [
            1505,
            4591
        ],
        [
            1879,
            5179
        ],
        [
            3880,
            521
        ],
        [
            3017,
            3181
        ],
        [
            8486,
            2370
        ],
        [
            4048,
            5011
        ],
        [
            6519,
            4800
        ],
        [
            7898,
            5093
        ],
        [
            3760,
            3278
        ],
        [
            5256,
            3296
        ],
        [
            2458,
            4137
        ],
        [
            5881,
            711
        ],
        [
            7934,
            6214
        ],
        [
            4312,
            3378
        ],
        [
            9701,
            4397
        ],
        [
            1352,
            4503
        ],
        [
            4259,
            3629
        ],
        [
            5765,
            2938
        ],
        [
            5755,
            3755
        ],
        [
            8654,
            5752
        ],
        [
            3535,
            7129
        ],
        [
            1868,
            866
        ],
        [
            9046,
            7855
        ],
        [
            7763,
            7791
        ],
        [
            566,
            7996
        ],
        [
            2038,
            1988
        ],
        [
            2971,
            6759
        ],
        [
            3470,
            5522
        ],
        [
            4846,
            4005
        ],
        [
            6017,
            7224
        ],
        [
            8597,
            7587
        ],
        [
            3624,
            3653
        ],
        [
            5681,
            4992
        ],
        [
            8379,
            4451
        ],
        [
            945,
            4964
        ],
        [
            4650,
            4460
        ],
        [
            3531,
            5545
        ],
        [
            7100,
            5377
        ],
        [
            7016,
            4868
        ],
        [
            9939,
            3375
        ],
        [
            1474,
            4204
        ],
        [
            3132,
            1142
        ],
        [
            6380,
            1389
        ],
        [
            2583,
            4888
        ],
        [
            6086,
            4254
        ],
        [
            8972,
            7829
        ],
        [
            1417,
            6461
        ],
        [
            9062,
            5114
        ],
        [
            6732,
            4814
        ],
        [
            5104,
            6877
        ],
        [
            5669,
            5084
        ],
        [
            9904,
            4316
        ],
        [
            2978,
            3050
        ],
        [
            6868,
            3653
        ],
        [
            4139,
            4296
        ],
        [
            1273,
            3208
        ],
        [
            3707,
            4373
        ],
        [
            9756,
            6867
        ],
        [
            8700,
            5543
        ],
        [
            8012,
            8098
        ],
        [
            6502,
            4323
        ],
        [
            1951,
            5788
        ],
        [
            3544,
            5810
        ],
        [
            5930,
            5723
        ],
        [
            3648,
            7644
        ],
        [
            5916,
            5552
        ],
        [
            3292,
            7226
        ],
        [
            1206,
            5403
        ],
        [
            1062,
            6770
        ],
        [
            2877,
            5061
        ]
    ]
}