{
    "instance_name": "N30_D3_G10000_grid_2",
    "n_customers": 30,
    "dimension": 3,
    "grid_size": 10000,
    "optimal_cost": 78725,
    "optimal_tour": [
        3,
        8,
        27,
        9,
        12,
        26,
        22,
        1,
        21,
        7,
        11,
        30,
        5,
        2,
        10,
        13,
        18,
        23,
        17,
        29,
        19,
        28,
        24,
        14,
        25,
        16,
        4,
        15,
        20,
        6
    ],
    "optimal_solver": "lkh",
    "instance_file_path": "c:\\TSP_ND_ML_Project\\instances\\N30_D3_G10000_grid_2.json",
    "concorde_length": 78725,
    "concorde_time_s": 0.6948201000341214,
    "concorde_tour": [
        1,
        22,
        26,
        12,
        9,
        27,
        8,
        3,
        6,
        20,
        15,
        4,
        16,
        25,
        14,
        24,
        28,
        19,
        29,
        17,
        23,
        18,
        13,
        10,
        2,
        5,
        30,
        11,
        7,
        21
    ],
    "lkh_length": 78725,
    "lkh_time_s": 0.04524969996418804,
    "lkh_tour": [
        3,
        8,
        27,
        9,
        12,
        26,
        22,
        1,
        21,
        7,
        11,
        30,
        5,
        2,
        10,
        13,
        18,
        23,
        17,
        29,
        19,
        28,
        24,
        14,
        25,
        16,
        4,
        15,
        20,
        6
    ],
    "lkh_gap_pct": 0.0
}