{
    "instance_name": "N500_D3_G1000_corn_4",
    "n_customers": 500,
    "dimension": 3,
    "grid_size": 1000,
    "optimal_cost": 10680,
    "optimal_tour": [
        333,
        86,
        308,
        217,
        175,
        69,
        449,
        7,
        433,
        234,
        44,
        189,
        128,
        177,
        110,
        260,
        226,
        361,
        293,
        410,
        77,
        341,
        129,
        319,
        313,
        398,
        471,
        404,
        327,
        368,
        397,
        434,
        130,
        249,
        134,
        98,
        332,
        206,
        380,
        61,
        115,
        292,
        375,
        321,
        3,
        271,
        407,
        462,
        351,
        221,
        48,
        473,
        193,
        363,
        204,
        469,
        268,
        459,
        311,
        296,
        208,
        171,
        446,
        106,
        242,
        256,
        111,
        262,
        491,
        194,
        81,
        133,
        113,
        136,
        499,
        328,
        482,
        30,
        331,
        155,
        403,
        414,
        339,
        245,
        107,
        255,
        440,
        401,
        160,
        144,
        39,
        431,
        344,
        498,
        497,
        364,
        357,
        282,
        383,
        49,
        149,
        146,
        29,
        474,
        412,
        199,
        209,
        207,
        306,
        100,
        118,
        202,
        214,
        181,
        31,
        478,
        222,
        254,
        24,
        350,
        285,
        456,
        435,
        265,
        220,
        352,
        395,
        153,
        35,
        244,
        230,
        156,
        275,
        378,
        261,
        167,
        392,
        257,
        280,
        235,
        420,
        330,
        450,
        52,
        178,
        45,
        338,
        358,
        9,
        40,
        437,
        466,
        161,
        43,
        381,
        276,
        494,
        55,
        480,
        104,
        28,
        26,
        176,
        386,
        123,
        96,
        22,
        210,
        400,
        489,
        165,
        463,
        16,
        273,
        405,
        147,
        70,
        426,
        460,
        32,
        174,
        372,
        243,
        87,
        415,
        159,
        248,
        444,
        95,
        427,
        479,
        413,
        465,
        53,
        229,
        64,
        84,
        324,
        89,
        27,
        71,
        103,
        279,
        152,
        418,
        198,
        294,
        360,
        67,
        82,
        488,
        197,
        154,
        122,
        283,
        355,
        388,
        314,
        423,
        277,
        50,
        251,
        196,
        223,
        301,
        396,
        269,
        2,
        36,
        278,
        121,
        451,
        343,
        454,
        393,
        60,
        370,
        476,
        180,
        11,
        266,
        17,
        83,
        131,
        307,
        250,
        484,
        135,
        63,
        290,
        458,
        316,
        163,
        457,
        205,
        335,
        142,
        74,
        150,
        6,
        185,
        59,
        8,
        325,
        289,
        212,
        78,
        140,
        362,
        270,
        253,
        54,
        148,
        157,
        295,
        102,
        127,
        495,
        377,
        73,
        5,
        430,
        373,
        57,
        137,
        263,
        337,
        281,
        303,
        448,
        467,
        291,
        443,
        138,
        417,
        322,
        112,
        188,
        125,
        213,
        66,
        139,
        72,
        187,
        487,
        238,
        172,
        240,
        239,
        46,
        492,
        297,
        320,
        366,
        99,
        326,
        143,
        38,
        164,
        258,
        411,
        228,
        10,
        151,
        166,
        493,
        340,
        367,
        21,
        241,
        186,
        305,
        79,
        342,
        105,
        486,
        119,
        349,
        225,
        490,
        436,
        347,
        109,
        246,
        455,
        299,
        108,
        394,
        428,
        416,
        216,
        88,
        348,
        409,
        51,
        114,
        232,
        424,
        286,
        442,
        92,
        33,
        470,
        215,
        284,
        336,
        298,
        421,
        371,
        233,
        183,
        354,
        302,
        382,
        468,
        334,
        304,
        376,
        120,
        402,
        365,
        429,
        483,
        391,
        353,
        85,
        231,
        389,
        477,
        14,
        252,
        445,
        18,
        259,
        91,
        300,
        25,
        97,
        200,
        267,
        475,
        237,
        20,
        359,
        75,
        192,
        439,
        182,
        441,
        12,
        15,
        384,
        472,
        318,
        1,
        310,
        329,
        4,
        47,
        379,
        425,
        453,
        272,
        37,
        203,
        13,
        485,
        58,
        94,
        191,
        247,
        168,
        438,
        312,
        76,
        432,
        41,
        309,
        158,
        218,
        419,
        169,
        101,
        496,
        179,
        356,
        387,
        190,
        162,
        224,
        369,
        374,
        170,
        34,
        141,
        23,
        399,
        93,
        500,
        68,
        173,
        80,
        195,
        116,
        464,
        345,
        461,
        317,
        126,
        227,
        42,
        315,
        90,
        211,
        274,
        124,
        132,
        422,
        288,
        323,
        145,
        346,
        481,
        452,
        447,
        56,
        264,
        19,
        236,
        390,
        219,
        65,
        406,
        408,
        184,
        117,
        62,
        385,
        287,
        201
    ],
    "optimal_solver": "lkh",
    "instance_file_path": "c:\\TSP_ND_ML_Project\\instances\\N500_D3_G1000_corn_4.json",
    "concorde_length": 10680,
    "concorde_time_s": 22.198004200006835,
    "concorde_tour": [
        1,
        310,
        329,
        4,
        47,
        379,
        425,
        453,
        272,
        37,
        203,
        13,
        485,
        58,
        15,
        12,
        441,
        182,
        439,
        192,
        75,
        359,
        20,
        237,
        475,
        267,
        200,
        284,
        336,
        298,
        421,
        97,
        25,
        300,
        91,
        259,
        18,
        445,
        252,
        14,
        477,
        389,
        231,
        85,
        353,
        120,
        334,
        402,
        304,
        483,
        376,
        468,
        391,
        429,
        365,
        382,
        354,
        302,
        183,
        233,
        371,
        215,
        470,
        33,
        442,
        92,
        286,
        424,
        232,
        114,
        51,
        409,
        348,
        88,
        216,
        416,
        428,
        394,
        108,
        299,
        455,
        246,
        347,
        109,
        436,
        490,
        225,
        349,
        119,
        486,
        105,
        342,
        79,
        305,
        186,
        21,
        241,
        367,
        340,
        493,
        166,
        151,
        258,
        38,
        143,
        10,
        228,
        164,
        411,
        326,
        99,
        366,
        320,
        297,
        492,
        46,
        239,
        240,
        172,
        238,
        487,
        187,
        72,
        139,
        66,
        213,
        125,
        188,
        112,
        322,
        417,
        138,
        443,
        291,
        467,
        448,
        303,
        281,
        337,
        263,
        150,
        6,
        137,
        57,
        373,
        430,
        5,
        73,
        377,
        495,
        127,
        102,
        295,
        157,
        148,
        54,
        253,
        362,
        270,
        140,
        78,
        212,
        325,
        289,
        59,
        8,
        185,
        74,
        142,
        335,
        205,
        457,
        163,
        316,
        458,
        290,
        63,
        135,
        484,
        250,
        307,
        131,
        36,
        278,
        83,
        17,
        266,
        11,
        180,
        476,
        370,
        393,
        60,
        454,
        343,
        451,
        121,
        2,
        269,
        396,
        301,
        223,
        196,
        251,
        50,
        277,
        423,
        314,
        388,
        355,
        283,
        122,
        154,
        197,
        488,
        82,
        67,
        360,
        294,
        198,
        103,
        418,
        71,
        64,
        152,
        89,
        279,
        27,
        84,
        324,
        229,
        53,
        465,
        413,
        427,
        479,
        95,
        444,
        248,
        159,
        415,
        87,
        243,
        372,
        174,
        32,
        460,
        426,
        70,
        147,
        405,
        273,
        16,
        463,
        165,
        400,
        489,
        210,
        22,
        96,
        123,
        420,
        386,
        176,
        26,
        28,
        104,
        480,
        55,
        494,
        276,
        381,
        43,
        161,
        466,
        437,
        40,
        9,
        358,
        338,
        45,
        178,
        52,
        450,
        330,
        235,
        280,
        257,
        456,
        285,
        435,
        378,
        352,
        395,
        261,
        153,
        275,
        392,
        220,
        156,
        265,
        230,
        35,
        244,
        167,
        350,
        24,
        222,
        254,
        478,
        31,
        181,
        214,
        202,
        118,
        100,
        306,
        207,
        209,
        199,
        412,
        474,
        29,
        146,
        149,
        49,
        383,
        282,
        357,
        364,
        497,
        498,
        344,
        431,
        39,
        144,
        160,
        401,
        440,
        255,
        107,
        245,
        339,
        414,
        403,
        155,
        331,
        30,
        482,
        328,
        499,
        136,
        113,
        133,
        81,
        194,
        491,
        111,
        262,
        256,
        242,
        106,
        446,
        171,
        208,
        296,
        311,
        459,
        268,
        469,
        204,
        363,
        193,
        473,
        48,
        221,
        351,
        462,
        407,
        271,
        3,
        61,
        206,
        115,
        292,
        321,
        375,
        380,
        332,
        98,
        134,
        249,
        130,
        434,
        397,
        368,
        327,
        404,
        471,
        398,
        313,
        319,
        129,
        341,
        77,
        410,
        293,
        361,
        226,
        260,
        110,
        177,
        128,
        189,
        44,
        234,
        433,
        7,
        449,
        69,
        175,
        217,
        308,
        86,
        333,
        201,
        287,
        385,
        62,
        117,
        184,
        408,
        406,
        65,
        219,
        236,
        390,
        19,
        264,
        56,
        132,
        124,
        422,
        288,
        323,
        274,
        145,
        346,
        447,
        481,
        452,
        90,
        211,
        315,
        42,
        227,
        126,
        317,
        461,
        345,
        464,
        116,
        195,
        80,
        173,
        68,
        500,
        93,
        399,
        23,
        141,
        34,
        170,
        374,
        369,
        162,
        224,
        190,
        179,
        356,
        496,
        387,
        101,
        169,
        384,
        419,
        218,
        158,
        309,
        41,
        432,
        438,
        168,
        247,
        191,
        94,
        312,
        76,
        472,
        318
    ],
    "lkh_length": 10680,
    "lkh_time_s": 451.2695631000097,
    "lkh_tour": [
        333,
        86,
        308,
        217,
        175,
        69,
        449,
        7,
        433,
        234,
        44,
        189,
        128,
        177,
        110,
        260,
        226,
        361,
        293,
        410,
        77,
        341,
        129,
        319,
        313,
        398,
        471,
        404,
        327,
        368,
        397,
        434,
        130,
        249,
        134,
        98,
        332,
        206,
        380,
        61,
        115,
        292,
        375,
        321,
        3,
        271,
        407,
        462,
        351,
        221,
        48,
        473,
        193,
        363,
        204,
        469,
        268,
        459,
        311,
        296,
        208,
        171,
        446,
        106,
        242,
        256,
        111,
        262,
        491,
        194,
        81,
        133,
        113,
        136,
        499,
        328,
        482,
        30,
        331,
        155,
        403,
        414,
        339,
        245,
        107,
        255,
        440,
        401,
        160,
        144,
        39,
        431,
        344,
        498,
        497,
        364,
        357,
        282,
        383,
        49,
        149,
        146,
        29,
        474,
        412,
        199,
        209,
        207,
        306,
        100,
        118,
        202,
        214,
        181,
        31,
        478,
        222,
        254,
        24,
        350,
        285,
        456,
        435,
        265,
        220,
        352,
        395,
        153,
        35,
        244,
        230,
        156,
        275,
        378,
        261,
        167,
        392,
        257,
        280,
        235,
        420,
        330,
        450,
        52,
        178,
        45,
        338,
        358,
        9,
        40,
        437,
        466,
        161,
        43,
        381,
        276,
        494,
        55,
        480,
        104,
        28,
        26,
        176,
        386,
        123,
        96,
        22,
        210,
        400,
        489,
        165,
        463,
        16,
        273,
        405,
        147,
        70,
        426,
        460,
        32,
        174,
        372,
        243,
        87,
        415,
        159,
        248,
        444,
        95,
        427,
        479,
        413,
        465,
        53,
        229,
        64,
        84,
        324,
        89,
        27,
        71,
        103,
        279,
        152,
        418,
        198,
        294,
        360,
        67,
        82,
        488,
        197,
        154,
        122,
        283,
        355,
        388,
        314,
        423,
        277,
        50,
        251,
        196,
        223,
        301,
        396,
        269,
        2,
        36,
        278,
        121,
        451,
        343,
        454,
        393,
        60,
        370,
        476,
        180,
        11,
        266,
        17,
        83,
        131,
        307,
        250,
        484,
        135,
        63,
        290,
        458,
        316,
        163,
        457,
        205,
        335,
        142,
        74,
        150,
        6,
        185,
        59,
        8,
        325,
        289,
        212,
        78,
        140,
        362,
        270,
        253,
        54,
        148,
        157,
        295,
        102,
        127,
        495,
        377,
        73,
        5,
        430,
        373,
        57,
        137,
        263,
        337,
        281,
        303,
        448,
        467,
        291,
        443,
        138,
        417,
        322,
        112,
        188,
        125,
        213,
        66,
        139,
        72,
        187,
        487,
        238,
        172,
        240,
        239,
        46,
        492,
        297,
        320,
        366,
        99,
        326,
        143,
        38,
        164,
        258,
        411,
        228,
        10,
        151,
        166,
        493,
        340,
        367,
        21,
        241,
        186,
        305,
        79,
        342,
        105,
        486,
        119,
        349,
        225,
        490,
        436,
        347,
        109,
        246,
        455,
        299,
        108,
        394,
        428,
        416,
        216,
        88,
        348,
        409,
        51,
        114,
        232,
        424,
        286,
        442,
        92,
        33,
        470,
        215,
        284,
        336,
        298,
        421,
        371,
        233,
        183,
        354,
        302,
        382,
        468,
        334,
        304,
        376,
        120,
        402,
        365,
        429,
        483,
        391,
        353,
        85,
        231,
        389,
        477,
        14,
        252,
        445,
        18,
        259,
        91,
        300,
        25,
        97,
        200,
        267,
        475,
        237,
        20,
        359,
        75,
        192,
        439,
        182,
        441,
        12,
        15,
        384,
        472,
        318,
        1,
        310,
        329,
        4,
        47,
        379,
        425,
        453,
        272,
        37,
        203,
        13,
        485,
        58,
        94,
        191,
        247,
        168,
        438,
        312,
        76,
        432,
        41,
        309,
        158,
        218,
        419,
        169,
        101,
        496,
        179,
        356,
        387,
        190,
        162,
        224,
        369,
        374,
        170,
        34,
        141,
        23,
        399,
        93,
        500,
        68,
        173,
        80,
        195,
        116,
        464,
        345,
        461,
        317,
        126,
        227,
        42,
        315,
        90,
        211,
        274,
        124,
        132,
        422,
        288,
        323,
        145,
        346,
        481,
        452,
        447,
        56,
        264,
        19,
        236,
        390,
        219,
        65,
        406,
        408,
        184,
        117,
        62,
        385,
        287,
        201
    ],
    "lkh_gap_pct": 0.0
}