{
    "instance_name": "N10_D3_G100_corn_17",
    "n_customers": 10,
    "dimension": 3,
    "grid_size": 100,
    "distribution_type": "corn",
    "generation_seed": 1710834,
    "coordinates": [
        [
            0,
            97,
            100
        ],
        [
            1,
            96,
            0
        ],
        [
            1,
            100,
            2
        ],
        [
            0,
            0,
            0
        ],
        [
            0,
            94,
            100
        ],
        [
            2,
            0,
            99
        ],
        [
            0,
            98,
            0
        ],
        [
            0,
            0,
            100
        ],
        [
            99,
            100,
            2
        ],
        [
            100,
            98,
            0
        ]
    ]
}