{
    "instance_name": "N80_D4_G1000_clus_18",
    "n_customers": 80,
    "dimension": 4,
    "grid_size": 1000,
    "distribution_type": "clus",
    "generation_seed": 1881839,
    "coordinates": [
        [
            797,
            181,
            328,
            811
        ],
        [
            809,
            882,
            326,
            190
        ],
        [
            703,
            282,
            268,
            756
        ],
        [
            760,
            305,
            335,
            306
        ],
        [
            565,
            321,
            319,
            261
        ],
        [
            787,
            871,
            285,
            125
        ],
        [
            509,
            804,
            369,
            247
        ],
        [
            803,
            827,
            370,
            884
        ],
        [
            747,
            863,
            244,
            215
        ],
        [
            553,
            283,
            203,
            878
        ],
        [
            769,
            817,
            293,
            810
        ],
        [
            569,
            252,
            192,
            814
        ],
        [
            578,
            324,
            223,
            225
        ],
        [
            726,
            855,
            323,
            248
        ],
        [
            777,
            243,
            257,
            167
        ],
        [
            580,
            843,
            296,
            771
        ],
        [
            603,
            293,
            379,
            224
        ],
        [
            453,
            912,
            391,
            262
        ],
        [
            594,
            151,
            409,
            846
        ],
        [
            516,
            387,
            329,
            272
        ],
        [
            473,
            252,
            378,
            92
        ],
        [
            790,
            304,
            361,
            203
        ],
        [
            756,
            304,
            266,
            257
        ],
        [
            640,
            315,
            268,
            808
        ],
        [
            576,
            246,
            266,
            852
        ],
        [
            718,
            349,
            367,
            912
        ],
        [
            589,
            263,
            328,
            227
        ],
        [
            552,
            796,
            334,
            253
        ],
        [
            790,
            200,
            361,
            855
        ],
        [
            590,
            861,
            340,
            106
        ],
        [
            531,
            349,
            303,
            880
        ],
        [
            695,
            355,
            269,
            116
        ],
        [
            511,
            827,
            302,
            284
        ],
        [
            502,
            319,
            318,
            838
        ],
        [
            534,
            329,
            273,
            206
        ],
        [
            688,
            886,
            399,
            248
        ],
        [
            724,
            892,
            285,
            285
        ],
        [
            560,
            949,
            371,
            221
        ],
        [
            781,
            890,
            389,
            204
        ],
        [
            573,
            938,
            303,
            814
        ],
        [
            557,
            917,
            278,
            212
        ],
        [
            696,
            848,
            339,
            158
        ],
        [
            456,
            298,
            254,
            150
        ],
        [
            788,
            815,
            333,
            801
        ],
        [
            495,
            284,
            299,
            833
        ],
        [
            816,
            894,
            214,
            842
        ],
        [
            768,
            818,
            326,
            216
        ],
        [
            467,
            163,
            359,
            249
        ],
        [
            452,
            861,
            378,
            181
        ],
        [
            613,
            898,
            292,
            272
        ],
        [
            748,
            173,
            345,
            693
        ],
        [
            817,
            191,
            288,
            234
        ],
        [
            809,
            934,
            292,
            779
        ],
        [
            568,
            807,
            416,
            173
        ],
        [
            503,
            308,
            178,
            855
        ],
        [
            654,
            803,
            237,
            885
        ],
        [
            790,
            175,
            267,
            837
        ],
        [
            498,
            881,
            226,
            803
        ],
        [
            763,
            261,
            334,
            219
        ],
        [
            724,
            239,
            372,
            904
        ],
        [
            772,
            275,
            362,
            212
        ],
        [
            569,
            904,
            310,
            168
        ],
        [
            426,
            324,
            323,
            801
        ],
        [
            741,
            310,
            279,
            847
        ],
        [
            707,
            256,
            193,
            177
        ],
        [
            511,
            876,
            415,
            231
        ],
        [
            777,
            282,
            300,
            821
        ],
        [
            710,
            762,
            322,
            226
        ],
        [
            621,
            310,
            224,
            852
        ],
        [
            591,
            1000,
            256,
            945
        ],
        [
            796,
            262,
            347,
            171
        ],
        [
            515,
            899,
            244,
            265
        ],
        [
            757,
            765,
            242,
            216
        ],
        [
            476,
            252,
            298,
            822
        ],
        [
            494,
            823,
            301,
            306
        ],
        [
            746,
            301,
            261,
            959
        ],
        [
            505,
            337,
            310,
            863
        ],
        [
            753,
            921,
            348,
            841
        ],
        [
            496,
            846,
            378,
            236
        ],
        [
            685,
            804,
            392,
            829
        ]
    ]
}