{
    "instance_name": "N80_D3_G10000_rand_14",
    "n_customers": 80,
    "dimension": 3,
    "grid_size": 10000,
    "distribution_type": "rand",
    "generation_seed": 1490721,
    "coordinates": [
        [
            780,
            3215,
            5927
        ],
        [
            6368,
            5505,
            2377
        ],
        [
            4418,
            4966,
            1140
        ],
        [
            7258,
            7202,
            2031
        ],
        [
            6153,
            1943,
            8587
        ],
        [
            9441,
            4505,
            7514
        ],
        [
            6259,
            3090,
            3509
        ],
        [
            8165,
            9067,
            7902
        ],
        [
            7001,
            8694,
            4849
        ],
        [
            7836,
            943,
            7970
        ],
        [
            1051,
            8068,
            4483
        ],
        [
            2024,
            6503,
            8758
        ],
        [
            3034,
            2656,
            9379
        ],
        [
            5286,
            6251,
            6617
        ],
        [
            6797,
            554,
            9273
        ],
        [
            1425,
            3577,
            1635
        ],
        [
            8214,
            6607,
            3308
        ],
        [
            7542,
            8231,
            8444
        ],
        [
            3259,
            3133,
            4496
        ],
        [
            7734,
            3577,
            7459
        ],
        [
            494,
            7854,
            8721
        ],
        [
            389,
            5718,
            8778
        ],
        [
            4403,
            8991,
            8017
        ],
        [
            7572,
            668,
            9644
        ],
        [
            2445,
            6591,
            9611
        ],
        [
            9787,
            3349,
            1387
        ],
        [
            1627,
            9008,
            8485
        ],
        [
            5189,
            2774,
            3368
        ],
        [
            2950,
            5348,
            4778
        ],
        [
            2857,
            289,
            6813
        ],
        [
            4800,
            6967,
            9200
        ],
        [
            6898,
            8740,
            7773
        ],
        [
            4395,
            7745,
            4317
        ],
        [
            5628,
            2786,
            4686
        ],
        [
            5204,
            2400,
            3251
        ],
        [
            9783,
            960,
            8753
        ],
        [
            7796,
            3490,
            6480
        ],
        [
            2386,
            1796,
            7137
        ],
        [
            462,
            4807,
            6172
        ],
        [
            1632,
            2914,
            4082
        ],
        [
            7899,
            4721,
            8141
        ],
        [
            3055,
            4211,
            2381
        ],
        [
            7141,
            512,
            4051
        ],
        [
            6280,
            9370,
            283
        ],
        [
            4206,
            7748,
            9838
        ],
        [
            5581,
            1394,
            9295
        ],
        [
            563,
            8526,
            1858
        ],
        [
            5778,
            3663,
            4307
        ],
        [
            4228,
            1278,
            7706
        ],
        [
            1896,
            7619,
            9284
        ],
        [
            542,
            4108,
            8550
        ],
        [
            9500,
            5057,
            545
        ],
        [
            2570,
            5735,
            5584
        ],
        [
            3424,
            5077,
            2467
        ],
        [
            3854,
            3102,
            2068
        ],
        [
            6271,
            9971,
            2378
        ],
        [
            1984,
            4732,
            7130
        ],
        [
            6402,
            5394,
            1282
        ],
        [
            7890,
            8855,
            8159
        ],
        [
            6679,
            6353,
            7563
        ],
        [
            7870,
            5896,
            1052
        ],
        [
            4734,
            200,
            5746
        ],
        [
            3863,
            2905,
            2944
        ],
        [
            2325,
            6456,
            5406
        ],
        [
            6608,
            7333,
            9836
        ],
        [
            6904,
            8853,
            3521
        ],
        [
            8482,
            8578,
            540
        ],
        [
            5250,
            2379,
            5723
        ],
        [
            7146,
            7981,
            5742
        ],
        [
            5378,
            9764,
            1059
        ],
        [
            118,
            8949,
            5549
        ],
        [
            9509,
            6809,
            7249
        ],
        [
            3863,
            7756,
            755
        ],
        [
            7374,
            7429,
            6172
        ],
        [
            3398,
            5711,
            6392
        ],
        [
            1042,
            7543,
            3286
        ],
        [
            4684,
            818,
            2090
        ],
        [
            6084,
            5775,
            4385
        ],
        [
            6313,
            9826,
            952
        ],
        [
            215,
            232,
            6214
        ]
    ]
}