{
    "instance_name": "N90_D3_G1000_ring_6",
    "n_customers": 90,
    "dimension": 3,
    "grid_size": 1000,
    "distribution_type": "ring",
    "generation_seed": 691732,
    "coordinates": [
        [
            780,
            218,
            293
        ],
        [
            768,
            666,
            246
        ],
        [
            790,
            789,
            669
        ],
        [
            706,
            771,
            879
        ],
        [
            792,
            300,
            236
        ],
        [
            752,
            758,
            222
        ],
        [
            672,
            200,
            96
        ],
        [
            708,
            802,
            665
        ],
        [
            248,
            228,
            294
        ],
        [
            150,
            785,
            714
        ],
        [
            233,
            772,
            242
        ],
        [
            745,
            768,
            316
        ],
        [
            826,
            776,
            786
        ],
        [
            753,
            759,
            760
        ],
        [
            783,
            823,
            237
        ],
        [
            321,
            199,
            390
        ],
        [
            784,
            824,
            222
        ],
        [
            285,
            202,
            718
        ],
        [
            231,
            867,
            693
        ],
        [
            885,
            226,
            243
        ],
        [
            273,
            245,
            692
        ],
        [
            684,
            725,
            257
        ],
        [
            710,
            251,
            780
        ],
        [
            186,
            352,
            858
        ],
        [
            741,
            795,
            214
        ],
        [
            667,
            313,
            746
        ],
        [
            858,
            279,
            726
        ],
        [
            750,
            263,
            233
        ],
        [
            233,
            698,
            718
        ],
        [
            181,
            793,
            729
        ],
        [
            263,
            710,
            746
        ],
        [
            728,
            825,
            146
        ],
        [
            690,
            305,
            224
        ],
        [
            273,
            280,
            743
        ],
        [
            782,
            761,
            773
        ],
        [
            745,
            222,
            259
        ],
        [
            658,
            270,
            728
        ],
        [
            235,
            710,
            211
        ],
        [
            241,
            363,
            787
        ],
        [
            663,
            221,
            236
        ],
        [
            248,
            699,
            298
        ],
        [
            771,
            255,
            194
        ],
        [
            832,
            819,
            771
        ],
        [
            358,
            694,
            303
        ],
        [
            199,
            732,
            733
        ],
        [
            787,
            733,
            233
        ],
        [
            233,
            180,
            738
        ],
        [
            250,
            719,
            801
        ],
        [
            760,
            267,
            220
        ],
        [
            322,
            817,
            224
        ],
        [
            771,
            307,
            274
        ],
        [
            820,
            801,
            748
        ],
        [
            260,
            261,
            702
        ],
        [
            730,
            266,
            698
        ],
        [
            845,
            687,
            223
        ],
        [
            288,
            184,
            277
        ],
        [
            740,
            297,
            776
        ],
        [
            616,
            748,
            693
        ],
        [
            816,
            804,
            344
        ],
        [
            807,
            805,
            675
        ],
        [
            794,
            284,
            807
        ],
        [
            261,
            135,
            277
        ],
        [
            709,
            846,
            786
        ],
        [
            813,
            254,
            678
        ],
        [
            676,
            267,
            762
        ],
        [
            735,
            775,
            238
        ],
        [
            269,
            802,
            764
        ],
        [
            762,
            705,
            756
        ],
        [
            225,
            775,
            262
        ],
        [
            773,
            224,
            242
        ],
        [
            740,
            219,
            722
        ],
        [
            723,
            313,
            778
        ],
        [
            734,
            294,
            721
        ],
        [
            266,
            720,
            229
        ],
        [
            686,
            732,
            253
        ],
        [
            749,
            204,
            227
        ],
        [
            793,
            778,
            240
        ],
        [
            298,
            249,
            212
        ],
        [
            665,
            317,
            694
        ],
        [
            823,
            328,
            736
        ],
        [
            298,
            179,
            175
        ],
        [
            732,
            811,
            202
        ],
        [
            227,
            714,
            768
        ],
        [
            775,
            271,
            343
        ],
        [
            226,
            738,
            265
        ],
        [
            728,
            214,
            779
        ],
        [
            229,
            265,
            778
        ],
        [
            280,
            255,
            689
        ],
        [
            208,
            889,
            253
        ],
        [
            254,
            304,
            826
        ]
    ]
}